{
  "name": "document-type-taxonomy",
  "version": "v1",
  "language": "zh-CN",
  "categories": [
    {
      "id": "law_regulation",
      "label": "法律法规",
      "definition": "法律、行政法规、部门规章、地方性法规、条例、办法、司法解释等。"
    },
    {
      "id": "standard_spec",
      "label": "标准/规范",
      "definition": "国家/行业/团体/企业标准、技术规范、验收规范、规程、指南性标准等。"
    },
    {
      "id": "contract_agreement",
      "label": "合同/协议",
      "definition": "合同、协议、条款、补充协议、采购/服务合同、保密协议等。"
    },
    {
      "id": "handbook_manual",
      "label": "手册/指南",
      "definition": "操作手册、使用说明、诊疗/工作指南、SOP、流程手册、FAQ 等。"
    },
    {
      "id": "book_textbook",
      "label": "图书/教材",
      "definition": "书籍、教材、培训教材、系统性长篇内容（非条款/非标准）。"
    },
    {
      "id": "policy_procedure",
      "label": "制度/流程",
      "definition": "管理制度、流程文件、内控文件、岗位职责、管理办法（非法律法规）。"
    },
    {
      "id": "report_whitepaper",
      "label": "报告/白皮书",
      "definition": "调研报告、技术报告、白皮书、评估报告、可行性研究等。"
    },
    {
      "id": "form_template",
      "label": "表单/模板",
      "definition": "表格、清单、记录表、检查表、合同/制度模板等。"
    },
    {
      "id": "other",
      "label": "综合/其他",
      "definition": "无法可靠归入上述类型，或跨类型混合内容。"
    }
  ]
}

